clickup_apiV2/__init__.py
clickup_apiV2/client.py
clickup_apiv2-0.0.8.dist-info/LICENSE
clickup_apiv2-0.0.8.dist-info/METADATA
clickup_apiv2-0.0.8.dist-info/WHEEL
clickup_apiv2-0.0.8.dist-info/top_level.txt
clickup_apiv2-0.0.8.dist-info/RECORD
