Metadata-Version: 2.2
Name: clickup-apiv2
Version: 0.0.8
Summary: A Python client for interacting with the ClickUp API V2.
Home-page: https://github.com/lorithai/clickup_apiV2
Author: Aleksander Hykkerud
Author-email: lorithai@gmail.com
Classifier: Programming Language :: Python :: 3
Classifier: License :: OSI Approved :: MIT License
Classifier: Operating System :: OS Independent
Requires-Python: >=3.6
License-File: LICENSE
Requires-Dist: requests
Dynamic: author
Dynamic: author-email
Dynamic: classifier
Dynamic: description
Dynamic: description-content-type
Dynamic: home-page
Dynamic: requires-dist
Dynamic: requires-python
Dynamic: summary
